LICENSE
README.md
setup.cfg
setup.py
lightup_airflow_provider/__init__.py
lightup_airflow_provider.egg-info/PKG-INFO
lightup_airflow_provider.egg-info/SOURCES.txt
lightup_airflow_provider.egg-info/dependency_links.txt
lightup_airflow_provider.egg-info/entry_points.txt
lightup_airflow_provider.egg-info/top_level.txt
lightup_airflow_provider/operators/__init__.py
lightup_airflow_provider/operators/lightup_base_operator.py
lightup_airflow_provider/operators/lightup_trigger_operator.py
lightup_airflow_provider/sensors/__init__.py
lightup_airflow_provider/sensors/lightup_base_sensor_operator.py
lightup_airflow_provider/sensors/lightup_trigger_result_sensor.py