Metadata-Version: 2.1
Name: lightup-airflow-provider
Version: 1.0.1
Summary: Lightup Airflow provider.
Home-page: https://www.lightup.ai/
Author: Lightup Data, Inc
Author-email: support@lightup.ai
License: Apache License 2.0
Platform: UNKNOWN
Classifier: Framework :: Apache Airflow
Classifier: Framework :: Apache Airflow :: Provider
Requires-Python: ~=3.9
License-File: LICENSE
